codustry/__init__.py
codustry/codustry.py
codustry/models/__init__.py
codustry/models/client.py
codustry/models/craftsman.py
codustry/models/project.py
codustry/models/team.py
codustry/protocals/__init__.py
codustry/protocals/inactive.py
codustry/rules/__init__.py
codustry/rules/etiquette/communication.py
codustry-0.1.0.dist-info/WHEEL
codustry-0.1.0.dist-info/METADATA
codustry-0.1.0.dist-info/RECORD
