Metadata-Version: 2.1
Name: codustry
Version: 0.1.0
Summary: codustry protocals
Home-page: https://github.com/codustry/ceps
Author: Nutchanon Ninyawee
Author-email: nutchanon@codustry.com
Requires-Python: >=3.9,<4.0
Classifier: Programming Language :: Python :: 3
Classifier: Programming Language :: Python :: 3.9
Requires-Dist: autoname (>=0.1.2,<0.2.0)
Requires-Dist: avajana (>=0.4.1,<0.5.0)
Requires-Dist: halo (>=0.0.30,<0.0.31)
Requires-Dist: pydantic (>=1.6.1,<2.0.0)
Project-URL: Repository, https://github.com/codustry/ceps
